organize.py
file_organizer-0.2.3.dist-info/METADATA
file_organizer-0.2.3.dist-info/RECORD
file_organizer-0.2.3.dist-info/WHEEL
file_organizer-0.2.3.dist-info/entry_points.txt
file_organizer-0.2.3.dist-info/top_level.txt
