Metadata-Version: 2.1
Name: file-organizer
Version: 0.2.3
Summary: A file organizer based on file suffixes and user chosen file extensions
Home-page: https://github.com/xlbruce/file-organizer
Author: Gilson de Paula
Author-email: gilsonsvieira93@gmail.com
License: MIT
Keywords: file,organizer
Platform: UNKNOWN
Classifier: Programming Language :: Python :: 3.7
Classifier: Operating System :: POSIX
Requires-Dist: Click
